macprefs/__init__.py
macprefs/__main__.py
macprefs/config.py
macprefs/constants.py
macprefs/exceptions.py
macprefs/filters/__init__.py
macprefs/filters/bad_domains.py
macprefs/filters/bad_keys.py
macprefs/filters/bad_keys_re.py
macprefs/main.py
macprefs/plist2defaults.py
macprefs/processing.py
macprefs/py.typed
macprefs/typing.py
macprefs/utils.py
macprefs-0.4.2.dist-info/METADATA
macprefs-0.4.2.dist-info/WHEEL
macprefs-0.4.2.dist-info/entry_points.txt
macprefs-0.4.2.dist-info/licenses/LICENSE.txt
macprefs-0.4.2.dist-info/RECORD
