Metadata-Version: 2.4
Name: macprefs
Version: 0.4.2
Summary: Command and library to export macOS preferences.
License-Expression: MIT
License-File: LICENSE.txt
Keywords: command line,macos,preferences,utilities
Author: Andrew Udvare
Author-email: audvare@gmail.com
Requires-Python: >=3.10,<4.0
Classifier: Development Status :: 4 - Beta
Classifier: Intended Audience :: Developers
Classifier: Programming Language :: Python
Classifier: Programming Language :: Python :: 3.10
Classifier: Programming Language :: Python :: 3.11
Classifier: Programming Language :: Python :: 3.12
Classifier: Programming Language :: Python :: 3.13
Classifier: Programming Language :: Python :: 3.14
Classifier: Typing :: Typed
Classifier: Environment :: MacOS X
Classifier: Intended Audience :: Information Technology
Classifier: Intended Audience :: System Administrators
Classifier: Operating System :: MacOS :: MacOS X
Classifier: Topic :: System :: Archiving :: Backup
Classifier: Topic :: System :: Systems Administration
Classifier: Topic :: Utilities
Requires-Dist: anyio (>=4.12.0,<5.0.0)
Requires-Dist: bascom (>=0.1.0,<0.2.0)
Requires-Dist: click (>=8.3.1,<9.0.0)
Requires-Dist: platformdirs (>=4.5.1,<5.0.0)
Requires-Dist: tomlkit (>=0.13.3,<0.14.0)
Requires-Dist: typing-extensions (>=4.15.0,<5.0.0)
Project-URL: Documentation, https://macprefs.readthedocs.org
Project-URL: Homepage, https://tatsh.github.io/macprefs/
Project-URL: Issues, https://github.com/Tatsh/macprefs/issues
Project-URL: Repository, https://github.com/Tatsh/macprefs
